streamlit_state_manager/__init__.py
streamlit_state_manager/manager.py
streamlit_state_manager-0.2.6.dist-info/licenses/LICENSE
streamlit_state_manager-0.2.6.dist-info/METADATA
streamlit_state_manager-0.2.6.dist-info/WHEEL
streamlit_state_manager-0.2.6.dist-info/top_level.txt
streamlit_state_manager-0.2.6.dist-info/RECORD
