Metadata-Version: 2.4
Name: streamlit-state-manager
Version: 0.2.6
Summary: A wrapper around Streamlit's session state for easier state management
Author-email: Stelios Georgaras <steliosgp13@gmail.com>
License: Apache License 2.0
Project-URL: Homepage, https://github.com/steliosgrs/streamlit-state-manager
Project-URL: Bug Tracker, https://github.com/steliosgrs/streamlit-state-manager/issues
Classifier: Programming Language :: Python :: 3
Classifier: License :: OSI Approved :: Apache Software License
Classifier: Operating System :: OS Independent
Requires-Python: >=3.9
License-File: LICENSE
Requires-Dist: streamlit>=1.30.0
Dynamic: license-file
